aipartnerupflow/__init__.py
aipartnerupflow/api/__init__.py
aipartnerupflow/api/app.py
aipartnerupflow/api/extensions.py
aipartnerupflow/api/main.py
aipartnerupflow/api/protocols.py
aipartnerupflow/api/a2a/__init__.py
aipartnerupflow/api/a2a/agent_executor.py
aipartnerupflow/api/a2a/custom_starlette_app.py
aipartnerupflow/api/a2a/event_queue_bridge.py
aipartnerupflow/api/a2a/server.py
aipartnerupflow/api/a2a/task_routes_adapter.py
aipartnerupflow/api/docs/__init__.py
aipartnerupflow/api/docs/openapi.py
aipartnerupflow/api/docs/swagger_ui.py
aipartnerupflow/api/mcp/__init__.py
aipartnerupflow/api/mcp/adapter.py
aipartnerupflow/api/mcp/resources.py
aipartnerupflow/api/mcp/server.py
aipartnerupflow/api/mcp/tools.py
aipartnerupflow/api/mcp/transport_http.py
aipartnerupflow/api/mcp/transport_stdio.py
aipartnerupflow/api/middleware/__init__.py
aipartnerupflow/api/middleware/db_session.py
aipartnerupflow/api/routes/__init__.py
aipartnerupflow/api/routes/base.py
aipartnerupflow/api/routes/docs.py
aipartnerupflow/api/routes/system.py
aipartnerupflow/api/routes/tasks.py
aipartnerupflow/cli/__init__.py
aipartnerupflow/cli/decorators.py
aipartnerupflow/cli/extension.py
aipartnerupflow/cli/main.py
aipartnerupflow/cli/commands/__init__.py
aipartnerupflow/cli/commands/daemon.py
aipartnerupflow/cli/commands/generate.py
aipartnerupflow/cli/commands/run.py
aipartnerupflow/cli/commands/serve.py
aipartnerupflow/cli/commands/tasks.py
aipartnerupflow/core/__init__.py
aipartnerupflow/core/decorators.py
aipartnerupflow/core/types.py
aipartnerupflow/core/base/__init__.py
aipartnerupflow/core/base/base_task.py
aipartnerupflow/core/config/__init__.py
aipartnerupflow/core/config/registry.py
aipartnerupflow/core/execution/__init__.py
aipartnerupflow/core/execution/dependency_resolver.py
aipartnerupflow/core/execution/errors.py
aipartnerupflow/core/execution/executor_registry.py
aipartnerupflow/core/execution/streaming_callbacks.py
aipartnerupflow/core/execution/task_creator.py
aipartnerupflow-0.9.0.dist-info/licenses/LICENSE
aipartnerupflow-0.9.0.dist-info/METADATA
aipartnerupflow-0.9.0.dist-info/WHEEL
aipartnerupflow-0.9.0.dist-info/entry_points.txt
aipartnerupflow-0.9.0.dist-info/top_level.txt
aipartnerupflow-0.9.0.dist-info/RECORD
