Metadata-Version: 2.4
Name: aipartnerupflow
Version: 0.9.0
Summary: Agent workflow orchestration and execution platform
Author-email: aipartnerup <tercel.yi@gmail.com>
License: Apache-2.0
Keywords: ai,agent,orchestration,workflow,task,crewai,a2a
Classifier: Development Status :: 4 - Beta
Classifier: Intended Audience :: Developers
Classifier: License :: OSI Approved :: Apache Software License
Classifier: Programming Language :: Python :: 3
Classifier: Programming Language :: Python :: 3.10
Classifier: Programming Language :: Python :: 3.11
Classifier: Programming Language :: Python :: 3.12
Requires-Python: >=3.10
License-File: LICENSE
Requires-Dist: pydantic>=2.0.0
Requires-Dist: pydantic-settings>=2.0.0
Requires-Dist: sqlalchemy>=2.0.0
Requires-Dist: alembic>=1.13.0
Requires-Dist: duckdb-engine>=0.10.0
Requires-Dist: pytz>=2024.1
Provides-Extra: a2a
Requires-Dist: fastapi>=0.115.0; extra == "a2a"
Requires-Dist: uvicorn[standard]>=0.34.2; extra == "a2a"
Requires-Dist: a2a-sdk[http-server]>=0.3.0; extra == "a2a"
Requires-Dist: httpx[socks]>=0.27.0; extra == "a2a"
Requires-Dist: aiohttp[speedups]>=3.9.0; extra == "a2a"
Requires-Dist: starlette>=0.27.0; extra == "a2a"
Requires-Dist: websockets>=12.0; extra == "a2a"
Requires-Dist: python-jose[cryptography]>=3.3.0; extra == "a2a"
Provides-Extra: cli
Requires-Dist: click>=8.0.0; extra == "cli"
Requires-Dist: rich>=13.0.0; extra == "cli"
Requires-Dist: typer>=0.9.0; extra == "cli"
Requires-Dist: python-dotenv>=1.0.0; extra == "cli"
Requires-Dist: nest_asyncio>=1.5.0; extra == "cli"
Provides-Extra: postgres
Requires-Dist: asyncpg>=0.29.0; extra == "postgres"
Requires-Dist: psycopg2-binary>=2.9.9; extra == "postgres"
Provides-Extra: crewai
Requires-Dist: crewai[tools]>=1.4.1; extra == "crewai"
Requires-Dist: aiodns>=3.6.1; extra == "crewai"
Provides-Extra: llm-key-config
Provides-Extra: ssh
Requires-Dist: asyncssh>=2.14.0; extra == "ssh"
Provides-Extra: docker
Requires-Dist: docker>=7.0.0; extra == "docker"
Provides-Extra: grpc
Requires-Dist: grpcio>=1.60.0; extra == "grpc"
Requires-Dist: grpcio-tools>=1.60.0; extra == "grpc"
Provides-Extra: mcp
Provides-Extra: llm
Requires-Dist: litellm>=1.0.0; extra == "llm"
Provides-Extra: dev
Requires-Dist: pytest>=7.0.0; extra == "dev"
Requires-Dist: pytest-asyncio>=0.21.0; extra == "dev"
Requires-Dist: pytest-cov>=4.0.0; extra == "dev"
Requires-Dist: black>=23.0.0; extra == "dev"
Requires-Dist: ruff>=0.1.0; extra == "dev"
Requires-Dist: mypy>=1.5.0; extra == "dev"
Requires-Dist: twine>=4.0.0; extra == "dev"
Requires-Dist: pre-commit>=3.0.0; extra == "dev"
Provides-Extra: all
Requires-Dist: aipartnerupflow[a2a,cli,crewai,docker,grpc,llm,llm-key-config,mcp,postgres,ssh]; extra == "all"
Dynamic: license-file
